README.rst
setup.py
tinp.py
tinp.egg-info/PKG-INFO
tinp.egg-info/SOURCES.txt
tinp.egg-info/dependency_links.txt
tinp.egg-info/top_level.txt