Metadata-Version: 1.1
Name: tinp
Version: 1.0.0a1
Summary: Library of input functions with type conversion
Home-page: https://github.com/dokelung/tinp
Author: dokelung
Author-email: dokelung@gmail.com
License: MIT
Keywords: input format type
Platform: UNKNOWN
Classifier: Development Status :: 3 - Alpha
Classifier: License :: OSI Approved :: MIT License
Classifier: Programming Language :: Python :: 3.3
Classifier: Programming Language :: Python :: 3.4
Classifier: Programming Language :: Python :: 3.5
Classifier: Programming Language :: Python :: 3.6
